LICENCE
README.md
setup.py
CombiCSP/CSP.py
CombiCSP/SolarGeometry.py
CombiCSP/Transmittance.py
CombiCSP/__init__.py
CombiCSP/economics.py
CombiCSP/misc.py
CombiCSP/solar_system_location.py
CombiCSP/solar_tower.py
CombiCSP/solar_trough.py
CombiCSP/storage.py
CombiCSP.egg-info/PKG-INFO
CombiCSP.egg-info/SOURCES.txt
CombiCSP.egg-info/dependency_links.txt
CombiCSP.egg-info/requires.txt
CombiCSP.egg-info/top_level.txt