Metadata-Version: 2.1
Name: CombiCSP
Version: 1.5.0
Summary: A package for Concentrated Solar Collectors and Solar Tower Calculations 
Home-page: https://github.com/npapnet/Combi_CSP/
Author: N. Papadakis, G. Arnaoutakis
Author-email: npapnet@gmail.com, g.e.arnaoutakis@gmail.com
Classifier: Programming Language :: Python :: 3
Classifier: License :: OSI Approved :: MIT License
Classifier: Operating System :: OS Independent
Requires-Python: >=3.8
License-File: LICENCE
